ampel/py.typed
ampel/content/NewSVGRecord.py
ampel/content/SVGRecord.py
ampel/core/adapter/AmpelPlotAdapter.py
ampel/demo/T4DemoSavePlot.py
ampel/model/PlotProperties.py
ampel/plot/create.py
build/lib/ampel/py.typed
build/lib/ampel/content/NewSVGRecord.py
build/lib/ampel/content/SVGRecord.py
build/lib/ampel/core/adapter/AmpelPlotAdapter.py
build/lib/ampel/demo/T4DemoSavePlot.py
build/lib/ampel/model/PlotProperties.py
build/lib/ampel/plot/create.py
build/lib/build/lib/ampel/py.typed
build/lib/build/lib/ampel/content/NewSVGRecord.py
build/lib/build/lib/ampel/content/SVGRecord.py
build/lib/build/lib/ampel/core/adapter/AmpelPlotAdapter.py
build/lib/build/lib/ampel/demo/T4DemoSavePlot.py
build/lib/build/lib/ampel/model/PlotProperties.py
build/lib/build/lib/ampel/plot/create.py
build/lib/build/lib/build/lib/ampel/py.typed
build/lib/build/lib/build/lib/ampel/content/NewSVGRecord.py
build/lib/build/lib/build/lib/ampel/content/SVGRecord.py
build/lib/build/lib/build/lib/ampel/core/adapter/AmpelPlotAdapter.py
build/lib/build/lib/build/lib/ampel/demo/T4DemoSavePlot.py
build/lib/build/lib/build/lib/ampel/model/PlotProperties.py
build/lib/build/lib/build/lib/ampel/plot/create.py
build/lib/build/lib/build/lib/build/lib/ampel/py.typed
build/lib/build/lib/build/lib/build/lib/ampel/content/NewSVGRecord.py
build/lib/build/lib/build/lib/build/lib/ampel/content/SVGRecord.py
build/lib/build/lib/build/lib/build/lib/ampel/core/adapter/AmpelPlotAdapter.py
build/lib/build/lib/build/lib/build/lib/ampel/demo/T4DemoSavePlot.py
build/lib/build/lib/build/lib/build/lib/ampel/model/PlotProperties.py
build/lib/build/lib/build/lib/build/lib/ampel/plot/create.py
build/lib/build/lib/build/lib/build/lib/build/lib/ampel/content/NewSVGRecord.py
build/lib/build/lib/build/lib/build/lib/build/lib/ampel/content/SVGRecord.py
build/lib/build/lib/build/lib/build/lib/build/lib/ampel/core/adapter/AmpelPlotAdapter.py
build/lib/build/lib/build/lib/build/lib/build/lib/ampel/demo/T4DemoSavePlot.py
ampel_plot-0.9.1.dist-info/METADATA
ampel_plot-0.9.1.dist-info/WHEEL
ampel_plot-0.9.1.dist-info/top_level.txt
ampel_plot-0.9.1.dist-info/RECORD
