Metadata-Version: 2.1
Name: ampel-plot
Version: 0.9.1
Requires-Python: >=3.10
Provides-Extra: mpl
Requires-Dist: matplotlib ; extra == 'mpl'
